pods/__init__.py
pods/a.out
pods/access.py
pods/config.py
pods/data_resources.json
pods/data_resources.yml
pods/datasets.py
pods/defaults.cfg
pods/football_teams.json
pods/mocap.py
pods/test
pods/test.c
pods/test.yaml
pods/testing/access_tests.py
pods/testing/datasets_tests.py
pods/testing/test_football_data.py
pods/testing/test_hdf5_loading.py
pods/util.py
pods-0.1.18.dist-info/AUTHORS.txt
pods-0.1.18.dist-info/LICENSE.txt
pods-0.1.18.dist-info/METADATA
pods-0.1.18.dist-info/WHEEL
pods-0.1.18.dist-info/entry_points.txt
pods-0.1.18.dist-info/RECORD
